kg_promtail/__init__.py
kg_promtail/builder.py
kg_promtail/configfile.py
kg_promtail/configfileext.py
kg_promtail/option.py
kg_promtail/py.typed
kg_promtail/tests/__init__.py
kg_promtail/tests/test_builder.py
kg_promtail-0.8.0.dist-info/LICENSE
kg_promtail-0.8.0.dist-info/METADATA
kg_promtail-0.8.0.dist-info/WHEEL
kg_promtail-0.8.0.dist-info/top_level.txt
kg_promtail-0.8.0.dist-info/RECORD
